__init__.py
whoishistory/__init__.py
whoishistory/api_client.py
whoishistory/requester.py
whoishistory/exceptions/__init__.py
whoishistory/exceptions/empty_response_exception.py
whoishistory/exceptions/server_error_exception.py
whoishistory/exceptions/unparsable_response_exception.py
whoishistory/models/__init__.py
whoishistory/models/historic.py
whois_history-1.0.3.dist-info/AUTHORS.rst
whois_history-1.0.3.dist-info/LICENSE
whois_history-1.0.3.dist-info/METADATA
whois_history-1.0.3.dist-info/WHEEL
whois_history-1.0.3.dist-info/top_level.txt
whois_history-1.0.3.dist-info/RECORD
