Metadata-Version: 2.1
Name: whois-history
Version: 1.0.3
Summary: Python client library for Whois History API.
Home-page: https://github.com/whois-api-llc/whois-history-py
Author: WHOIS API, Inc
Author-email: support@whoisxmlapi.com
License: MIT
Keywords: whois,api,whois history,whoisxmlapi
Platform: UNKNOWN
Classifier: Development Status :: 5 - Production/Stable
Classifier: Intended Audience :: Developers
Classifier: License :: OSI Approved :: MIT License
Classifier: Operating System :: Unix
Classifier: Operating System :: POSIX
Classifier: Operating System :: Microsoft :: Windows
Classifier: Programming Language :: Python
Classifier: Programming Language :: Python :: 3
Classifier: Programming Language :: Python :: 3.6
Classifier: Programming Language :: Python :: 3.7
Classifier: Programming Language :: Python :: 3.8
Classifier: Topic :: Utilities
Requires-Python: ~=3.6
Requires-Dist: requests
Provides-Extra: dev
Requires-Dist: mock ; extra == 'dev'
Requires-Dist: tox ; extra == 'dev'
